{
  "schemaVersion": 1,
  "id": "fabricenchantments",
  "version": "${version}",

  "name": "Fabric Enchantments",
  "description": "Fabric Enchantments adds a plethora of custom Enchantments to the Fabric Loader",
  "authors": [
    "Me!"
  ],
  "contact": {
    "homepage": "https://broman.dev/",
    "sources": "https://github.com/broman/FabricEnchantments"
  },

  "license": "CC0-1.0",
  "icon": "assets/fabricenchantments/icon.png",

  "environment": "*",
  "entrypoints": {
    "main": [
      "dev.broman.fabricenchantments.FabricEnchantments"
    ]
  },
  "mixins": [
    "fabricenchantments.mixins.json"
  ],

  "depends": {
    "fabricloader": ">=0.7.4",
    "fabric": "*",
    "minecraft": "1.16.x"
  },
  "suggests": {
    "another-mod": "*"
  }
}
